{
  "substitutions": [
    {
      "substring": "CERODOSBÉ",
      "replacement": "02B"
    },
    {
      "substring": "EL",
      "replacement": "L"
    },
    {
      "substring": "EN",
      "replacement": "N"
    },
    {
      "substring": "SE",
      "replacement": "C"
    },
    {
      "substring": "SIGLO",
      "replacement": "S"
    },
    {
      "substring": "SIGLOS",
      "replacement": "S"
    },
    {
      "substring": "VATIO",
      "replacement": "W"
    },
    {
      "substring": "VATIOS",
      "replacement": "W"
    },
    {
      "substring": "VOLTIOS",
      "replacement": "V"
    },
    {
      "substring": "ZEROZEROZERO",
      "replacement": "000"
    }
  ]
}
